{
  "type": "header",
  "name": "t:static_sections.header.name",
  "sections": {
    "announcement": {
      "type": "announcement-bar",
      "blocks": {
        "announcement-1": {
          "type": "text",
          "settings": {
            "text": "Receive a preview in 24 Hours, With Delivery 48 Hours later"
          }
        }
      },
      "block_order": [
        "announcement-1"
      ],
      "settings": {
        "color_palette": "light_2",
        "height": "s",
        "font_size": "14px",
        "enable_slider_arrows": true,
        "enable_slider_autoplay": false,
        "slider_autoplay_seconds": 3
      }
    },
    "header": {
      "type": "header",
      "blocks": {
        "df399deb-b366-4aa3-bd2b-9a8c680d9a74": {
          "type": "promo_banners",
          "disabled": true,
          "settings": {
            "menu_item": "Shop by Occasion",
            "height": "size-s",
            "enable_custom_height": false,
            "custom_height": 250,
            "image_zoom": false,
            "show_content_below": false,
            "layout": "columns",
            "enable_banner_1": true,
            "image_1": "shopify:\/\/shop_images\/Ornament_Desktop-1.jpg",
            "overlay_opacity_1": 0,
            "color_palette_1": "white",
            "button_color_palette_1": "accent",
            "text_position_1": "text-center",
            "title_1": "",
            "title_font_1": "primary",
            "title_size_1": "h2",
            "enable_custom_text_styling_1": false,
            "title_color_palette_1": "black",
            "title_weight_1": "700",
            "subtitle_1": "",
            "subtitle_font_1": "secondary",
            "subtitle_size_1": "h2",
            "enable_custom_sub_styling_1": false,
            "subtitle_color_palette_1": "black",
            "subtitle_weight_1": "400",
            "text_1": "",
            "enable_custom_font_styling_1": false,
            "font_size_1": "16px",
            "link_text_1": "Button",
            "link_url_1": "",
            "show_link_1": false,
            "enable_banner_2": false,
            "overlay_opacity_2": 0,
            "color_palette_2": "white",
            "button_color_palette_2": "accent",
            "text_position_2": "text-center",
            "title_2": "Image banner",
            "title_font_2": "primary",
            "title_size_2": "h2",
            "enable_custom_text_styling_2": false,
            "title_color_palette_2": "black",
            "title_weight_2": "700",
            "subtitle_2": "",
            "subtitle_font_2": "secondary",
            "subtitle_size_2": "h2",
            "enable_custom_sub_styling_2": false,
            "subtitle_color_palette_2": "black",
            "subtitle_weight_2": "400",
            "text_2": "<p>Give customers details about the banner image(s)<\/p>",
            "enable_custom_font_styling_2": false,
            "font_size_2": "16px",
            "link_text_2": "Button",
            "link_url_2": "",
            "show_link_2": false,
            "layout_mobile": "rows",
            "mobile_height": "size-s"
          }
        },
        "header-block-usp-1": {
          "type": "usp",
          "settings": {
            "usp": "<p>Give your customers details about your online store<\/p>",
            "show_check": true
          }
        },
        "header-block-usp-2": {
          "type": "usp",
          "disabled": true,
          "settings": {
            "usp": "<p>Give your customers more details about your online store<\/p>",
            "show_check": true
          }
        },
        "header-block-button-1": {
          "type": "button",
          "disabled": true,
          "settings": {
            "show_mobile": false,
            "button_menu": "main-menu",
            "button_color": "accent",
            "button_style": "plain"
          }
        }
      },
      "block_order": [
        "df399deb-b366-4aa3-bd2b-9a8c680d9a74",
        "header-block-usp-1",
        "header-block-usp-2",
        "header-block-button-1"
      ],
      "custom_css": [
        "ul li a {font-size: 16px !important ;}"
      ],
      "settings": {
        "layout": "layout_4",
        "width": 2000,
        "header_height": "109px|90px",
        "top_bar_color": "white",
        "header_color": "white",
        "search_color": "white",
        "menubar_color": "white",
        "show_top_bar": false,
        "top_bar_font_size": "14px",
        "navbar_menu_item_text": "Contact us",
        "navbar_menu_item_link": "shopify:\/\/pages\/contact",
        "enable_usp_slider": false,
        "enable_usp_slider_arrows": true,
        "enable_usp_slider_autoplay": true,
        "usp_slider_autoplay_seconds": 3,
        "logo": "shopify:\/\/shop_images\/sample_598x_55d2454a-af8a-4a4e-b1a4-d82628803bcb.webp",
        "logo_width": 290,
        "enable_country_selector": false,
        "enable_language_selector": true,
        "searchbar_font_size": "14px",
        "searchbar_height": 45,
        "enable_sticky_header": false,
        "sticky": "sticky-header",
        "cart_icon": "cart|e903",
        "cart_icon_color": "accent",
        "menubar_menu": "new-mega-menu",
        "menubar_height": "45px",
        "menu_layout": "mega",
        "show_dropdown_images": false,
        "show_dropdown_images_autofill": true,
        "menubar_alignment": "center",
        "menubar_border": false,
        "menubar_border_width": "wide",
        "menubar_border_color": "#f4f4f4",
        "main_menu_items_clickable": true,
        "menubar_caps": false,
        "sale_highlight": true,
        "menu_font": "body",
        "menu_font_weight": "400",
        "menu_font_size": 16,
        "menu_letter_spacing": 0,
        "menu_items_limit": 5,
        "main_menu_show_lines": true,
        "menu_subs_font": "secondary",
        "enable_menu_subs_font_size": false,
        "menu_subs_font_size": 16,
        "extra_image_width": 130,
        "extra_image_link": "",
        "disable_online_store": false,
        "logo_width_mobile": 140,
        "search_compact_mobile": false
      }
    }
  },
  "order": [
    "announcement",
    "header"
  ]
}
